README.rst
setup.cfg
setup.py
remoot/__init__.py
remoot/deferutils.py
remoot/pythonstarter.py
remoot/smartstarter.py
remoot/sourstarter.py
remoot/ssh.py
remoot/starter.py
remoot/test_credentials.py
remoot/test_smartstarter.py
remoot/test_sourstarter.py
remoot/test_ssh.py
remoot/test_starter.py
remoot/test_ziploader.py
remoot/ziploader.py
remoot.egg-info/PKG-INFO
remoot.egg-info/SOURCES.txt
remoot.egg-info/dependency_links.txt
remoot.egg-info/requires.txt
remoot.egg-info/top_level.txt