Metadata-Version: 1.0
Name: remoot
Version: 2.1.4
Summary: Remotely boots Python interpreters and establishes remote invocation capability with them.
Home-page: http://www.s-mueller.ch
Author: Stefan C. Mueller
Author-email: stefan.mueller@fhnw.ch
License: UNKNOWN
Platform: UNKNOWN
